MANIFEST.in
README.rst
setup.py
collective/__init__.py
collective.labels.egg-info/PKG-INFO
collective.labels.egg-info/SOURCES.txt
collective.labels.egg-info/dependency_links.txt
collective.labels.egg-info/entry_points.txt
collective.labels.egg-info/namespace_packages.txt
collective.labels.egg-info/not-zip-safe
collective.labels.egg-info/requires.txt
collective.labels.egg-info/top_level.txt
collective/labels/__init__.py
collective/labels/adapters.zcml
collective/labels/config.py
collective/labels/configure.zcml
collective/labels/indexer.py
collective/labels/interfaces.py
collective/labels/jar.py
collective/labels/labeling.py
collective/labels/lawgiver.zcml
collective/labels/permissions.zcml
collective/labels/profiles.zcml
collective/labels/setuphandler.py
collective/labels/testing.py
collective/labels/utils.py
collective/labels/Extensions/install.py
collective/labels/browser/__init__.py
collective/labels/browser/configure.zcml
collective/labels/browser/labeling.py
collective/labels/browser/labelsjar.py
collective/labels/browser/resources/edit_labels.png
collective/labels/browser/resources/ftw-labels.css
collective/labels/browser/resources/ftw-labels.js
collective/labels/browser/resources/select2-spinner.gif
collective/labels/browser/resources/select2.css
collective/labels/browser/resources/select2.min.js
collective/labels/browser/resources/select2.png
collective/labels/browser/resources/select2x2.png
collective/labels/browser/resources/settings.png
collective/labels/browser/templates/edit_label.pt
collective/labels/locales/ftw.labels.pot
collective/labels/locales/de/LC_MESSAGES/ftw.labels.mo
collective/labels/locales/de/LC_MESSAGES/ftw.labels.po
collective/labels/locales/fr/LC_MESSAGES/ftw.labels.mo
collective/labels/locales/fr/LC_MESSAGES/ftw.labels.po
collective/labels/portlets/__init__.py
collective/labels/portlets/assignments.py
collective/labels/portlets/configure.zcml
collective/labels/portlets/interfaces.py
collective/labels/portlets/labeljar.pt
collective/labels/portlets/labeljar.py
collective/labels/profiles/default/cssregistry.xml
collective/labels/profiles/default/ftw.labels.setuphandlers.txt
collective/labels/profiles/default/jsregistry.xml
collective/labels/profiles/default/metadata.xml
collective/labels/profiles/default/portlets.xml
collective/labels/profiles/default/rolemap.xml
