Metadata-Version: 2.1
Name: collective.labels
Version: 3.0.0a1
Summary: A Plone addon for labels.
Home-page: https://github.com/collective/collective.labels
Author: 4teamwork AG
Author-email: mailto:info@4teamwork.ch
License: GPL2
Keywords: collective labels
Classifier: Framework :: Plone
Classifier: Framework :: Plone :: 6.1
Classifier: Programming Language :: Python :: 3
Classifier: Intended Audience :: Developers
Classifier: Topic :: Software Development :: Libraries :: Python Modules
Provides-Extra: tests
